qenerate/__init__.py
qenerate/cli.py
qenerate/core/__init__.py
qenerate/core/code_command.py
qenerate/core/feature_flag_parser.py
qenerate/core/introspection_command.py
qenerate/core/plugin.py
qenerate/core/preprocessor.py
qenerate/core/unwrapper.py
qenerate/plugins/__init__.py
qenerate/plugins/pydantic/__init__.py
qenerate/plugins/pydantic/mapper.py
qenerate/plugins/pydantic/plugin.py
qenerate/plugins/pydantic/typed_ast.py
qenerate-0.9.1.dist-info/METADATA
qenerate-0.9.1.dist-info/WHEEL
qenerate-0.9.1.dist-info/entry_points.txt
qenerate-0.9.1.dist-info/licenses/LICENSE
qenerate-0.9.1.dist-info/RECORD
