Metadata-Version: 2.4
Name: qenerate
Version: 0.9.1
Summary: Code Generator for GraphQL Query and Fragment Data Classes
Project-URL: homepage, https://github.com/app-sre/qenerate
Project-URL: repository, https://github.com/app-sre/qenerate
Project-URL: documentation, https://github.com/app-sre/qenerate
Author-email: Red Hat - Service Delivery - AppSRE <sd-app-sre@redhat.com>
License: Apache 2.0
License-File: LICENSE
Requires-Python: >=3.12
Requires-Dist: graphql-core~=3.2.5
Requires-Dist: requests>=2.32.3
